mip_utils/__init__.py
mip_utils/exceptions.py
mip_utils/logging_formatter.py
mip_utils/ticdat_types.py
mip_utils/ticdat_utils.py
mip_utils-0.1.1.dist-info/LICENSE
mip_utils-0.1.1.dist-info/METADATA
mip_utils-0.1.1.dist-info/WHEEL
mip_utils-0.1.1.dist-info/RECORD
