Metadata-Version: 2.1
Name: mip-utils
Version: 0.1.1
Summary: A utility package designed to enhance workflows projects that use ticdat.
License: LICENSE
Author: Mip Wise
Author-email: contact@mipwise.com
Requires-Python: >=3.10,<4.0
Classifier: License :: Other/Proprietary License
Classifier: Programming Language :: Python :: 3
Classifier: Programming Language :: Python :: 3.10
Classifier: Programming Language :: Python :: 3.11
Classifier: Programming Language :: Python :: 3.12
Classifier: Programming Language :: Python :: 3.13
Requires-Dist: poetry-dynamic-versioning (>=1.4.1,<2.0.0)
